captif_cpx/__init__.py
captif_cpx/logging.py
captif_cpx/structures/__init__.py
captif_cpx/structures/gps.py
captif_cpx/structures/slowdata.py
captif_cpx-0.2.dist-info/LICENSE
captif_cpx-0.2.dist-info/WHEEL
captif_cpx-0.2.dist-info/METADATA
captif_cpx-0.2.dist-info/RECORD
