Metadata-Version: 2.1
Name: captif-cpx
Version: 0.2
Summary: 
Home-page: https://github.com/johnbullnz/pyrsona
License: MIT
Author: John Bull
Author-email: john.bull@nzta.govt.nz
Requires-Python: >=3.9,<4.0
Classifier: License :: OSI Approved :: MIT License
Classifier: Programming Language :: Python :: 3
Classifier: Programming Language :: Python :: 3.10
Classifier: Programming Language :: Python :: 3.9
Requires-Dist: SoundFile (>=0.10.3,<0.11.0)
Requires-Dist: black (>=22.3.0,<23.0.0)
Requires-Dist: pandas (>=1.4.2,<2.0.0)
Requires-Dist: pyramm (>=1.13,<2.0)
Requires-Dist: pyrsona (>=0.4,<0.5)
